HISTORY.rst
LICENSE
MANIFEST.in
README.rst
example.py
setup.cfg
setup.py
docs/Makefile
docs/source/conf.py
docs/source/contributing.rst
docs/source/index.rst
docs/source/ports.rst
docs/source/usage.rst
docs/source/reference/api.rst
docs/source/reference/mobileclient.rst
docs/source/reference/musicmanager.rst
docs/source/reference/protocol.rst
docs/source/reference/webclient.rst
gmusicapi/__init__.py
gmusicapi/_version.py
gmusicapi/compat.py
gmusicapi/exceptions.py
gmusicapi/session.py
gmusicapi.egg-info/PKG-INFO
gmusicapi.egg-info/SOURCES.txt
gmusicapi.egg-info/dependency_links.txt
gmusicapi.egg-info/not-zip-safe
gmusicapi.egg-info/requires.txt
gmusicapi.egg-info/top_level.txt
gmusicapi/clients/__init__.py
gmusicapi/clients/mobileclient.py
gmusicapi/clients/musicmanager.py
gmusicapi/clients/shared.py
gmusicapi/clients/webclient.py
gmusicapi/gmtools/__init__.py
gmusicapi/gmtools/tools.py
gmusicapi/protocol/__init__.py
gmusicapi/protocol/download_pb2.py
gmusicapi/protocol/locker_pb2.py
gmusicapi/protocol/mobileclient.py
gmusicapi/protocol/musicmanager.py
gmusicapi/protocol/shared.py
gmusicapi/protocol/uits_pb2.py
gmusicapi/protocol/upload_pb2.py
gmusicapi/protocol/webclient.py
gmusicapi/test/__init__.py
gmusicapi/test/audiotest_small.mp3
gmusicapi/test/fetchartist.jsarray
gmusicapi/test/imagetest_10x10_check.png
gmusicapi/test/local_tests.py
gmusicapi/test/rewrite_audiotest_tags.py
gmusicapi/test/run_tests.py
gmusicapi/test/searchresult.jsarray
gmusicapi/test/server_tests.py
gmusicapi/test/utils.py
gmusicapi/utils/__init__.py
gmusicapi/utils/counter.py
gmusicapi/utils/jsarray.py
gmusicapi/utils/utils.py