Metadata-Version: 1.1
Name: gmusicapi
Version: 7.0.0
Summary: An unofficial api for Google Play Music.
Home-page: http://pypi.python.org/pypi/gmusicapi/
Author: Simon Weber
Author-email: simon@simonmweber.com
License: Copyright (c) 2015, Simon Weber
